polarspark/__init__.py
polarspark/_globals.py
polarspark/_typing.pyi
polarspark/accumulators.py
polarspark/conf.py
polarspark/context.py
polarspark/files.py
polarspark/join.py
polarspark/loose_version.py
polarspark/rdd.py
polarspark/resultiterable.py
polarspark/serializers.py
polarspark/storagelevel.py
polarspark/traceback_utils.py
polarspark/util.py
polarspark/cloudpickle/__init__.py
polarspark/cloudpickle/cloudpickle.py
polarspark/cloudpickle/cloudpickle_fast.py
polarspark/cloudpickle/compat.py
polarspark/errors/__init__.py
polarspark/errors/error_classes.py
polarspark/errors/utils.py
polarspark/errors/exceptions/__init__.py
polarspark/errors/exceptions/base.py
polarspark/errors/exceptions/captured.py
polarspark/errors/exceptions/connect.py
polarspark/errors/tests/__init__.py
polarspark/errors/tests/test_errors.py
polarspark/functions/__init__.py
polarspark/sql/__init__.py
polarspark/sql/_typing.pyi
polarspark/sql/catalog.py
polarspark/sql/column.py
polarspark/sql/conf.py
polarspark/sql/context.py
polarspark/sql/dataframe.py
polarspark/sql/functions.py
polarspark/sql/group.py
polarspark/sql/readwriter.py
polarspark/sql/session.py
polarspark/sql/types.py
polarspark/sql/utils.py
polarspark/sql/window.py
polarspark/sql/_internal/__init__.py
polarspark/sql/_internal/catalog/__init__.py
polarspark/sql/_internal/catalog/in_memory_catalog.py
polarspark/sql/_internal/catalog/utils.py
polarspark/sql/_internal/parser/__init__.py
polarspark/sql/_internal/parser/ast.py
polarspark/sql/_internal/parser/ddl.py
polarspark/sql/_internal/parser/models.py
polarspark/sql/_internal/parser/parser.py
polarspark/sql/pandas/__init__.py
polarspark/sql/pandas/conversion.py
polarspark/sql/pandas/group_ops.py
polarspark/sql/pandas/map_ops.py
polarspark/sql/pandas/serializers.py
polarspark/sql/pandas/types.py
polarspark/sql/pandas/utils.py
polarspark/sql/streaming/__init__.py
polarspark/sql/streaming/file_watcher.py
polarspark/sql/streaming/listener.py
polarspark/sql/streaming/query.py
polarspark-0.2.1.dist-info/licenses/LICENSE
polarspark-0.2.1.dist-info/METADATA
polarspark-0.2.1.dist-info/WHEEL
polarspark-0.2.1.dist-info/top_level.txt
polarspark-0.2.1.dist-info/RECORD
