Metadata-Version: 2.4
Name: polarspark
Version: 0.2.1
Summary: Apache Spark on Polars
Home-page: https://github.com/khalidmammadov/polarspark
Author: Khalid Mammadov
Author-email: Khalid Mammadov <xmamedov@gmail.com>
Project-URL: Homepage, https://github.com/khalidmammadov/polarspark
Project-URL: Issues, https://github.com/khalidmammadov/polarspark/issues
Classifier: Programming Language :: Python :: 3
Classifier: License :: OSI Approved :: MIT License
Classifier: Operating System :: OS Independent
Requires-Python: >=3.9
License-File: LICENSE
Requires-Dist: pandas>=2.2.3
Requires-Dist: numpy>=1.21
Requires-Dist: polars==1.33.1
Requires-Dist: pyarrow>=4.0.0
Requires-Dist: tzlocal==5.2
Requires-Dist: deltalake>=1.0.0
Requires-Dist: watchdog
Requires-Dist: sqlglot
Dynamic: author
Dynamic: home-page
Dynamic: license-file
Dynamic: requires-python
